README.md
pyproject.toml
setup.cfg
setup.py
test/__init__.py
test/test_class_utils.py
test/test_finalize.py
test/test_graph.py
test/test_tunable.py
test/test_variable.py
tuneit/__init__.py
tuneit/class_utils.py
tuneit/finalize.py
tuneit/graph.py
tuneit/meta.py
tuneit/tunable.py
tuneit/variable.py
tuneit.egg-info/PKG-INFO
tuneit.egg-info/SOURCES.txt
tuneit.egg-info/dependency_links.txt
tuneit.egg-info/requires.txt
tuneit.egg-info/top_level.txt
tuneit/tools/__init__.py
tuneit/tools/base.py
tuneit/tools/check.py
tuneit/tools/time.py