Metadata-Version: 2.1
Name: tuneit
Version: 0.0.4
Summary: tuneit: tune, benchmark and crosscheck
Home-page: https://lyncs-api.github.io
Author: Simone Bacchio
Author-email: s.bacchio@gmail.com
License: UNKNOWN
Download-URL: https://github.com/Lyncs-API/tuneit
Keywords: benchmark,tuneit:,tune,,crosscheck
Platform: UNKNOWN
Classifier: Development Status :: 2 - Pre-Alpha
Classifier: Intended Audience :: Developers
Classifier: Intended Audience :: Education
Classifier: Intended Audience :: Science/Research
Classifier: License :: OSI Approved :: BSD License
Classifier: Natural Language :: English
Classifier: Operating System :: Unix
Classifier: Programming Language :: C
Classifier: Programming Language :: C++
Classifier: Programming Language :: Python :: 3 :: Only
Classifier: Topic :: Scientific/Engineering :: Physics
Provides-Extra: graph
Provides-Extra: test
Provides-Extra: all
